amitkh_wordle/solutions.txt
amitkh_wordle/utils.py
amitkh_wordle/wordle.py
amitkh_wordle/words.txt
amitkh_wordle-0.3.0.dist-info/entry_points.txt
amitkh_wordle-0.3.0.dist-info/WHEEL
amitkh_wordle-0.3.0.dist-info/METADATA
amitkh_wordle-0.3.0.dist-info/RECORD
